sumatra/__init__.py
sumatra/client.py
sumatra_sdk-1.2.0.dist-info/LICENSE
sumatra_sdk-1.2.0.dist-info/METADATA
sumatra_sdk-1.2.0.dist-info/WHEEL
sumatra_sdk-1.2.0.dist-info/top_level.txt
sumatra_sdk-1.2.0.dist-info/RECORD
