Metadata-Version: 2.1
Name: sumatra-sdk
Version: 1.2.0
Summary: Sumatra Python SDK
Home-page: https://sumatra.ai
Author: Sumatra
Author-email: support@sumatra.ai
License: MIT
Platform: any
Classifier: Programming Language :: Python :: 3
Classifier: Operating System :: OS Independent
Classifier: License :: Other/Proprietary License
Requires-Python: >=3.7
License-File: LICENSE
Requires-Dist: httpx
